pymata4/__init__.py
pymata4/custompymata4.py
pymata4/pin_data.py
pymata4/private_constants.py
pymata4/pymata4.py
pymata4-1.15.dist-info/METADATA
pymata4-1.15.dist-info/WHEEL
pymata4-1.15.dist-info/top_level.txt
pymata4-1.15.dist-info/RECORD
