Metadata-Version: 2.1
Name: pymata4
Version: 1.15
Summary: A Python Protocol Abstraction Library For Arduino Firmata
Home-page: https://github.com/MrYsLab/pymata4
Author: Alan Yorinks
Author-email: MisterYsLab@gmail.com
License: UNKNOWN
Download-URL: https://github.com/MrYsLab/pymata4
Keywords: Firmata,Arduino,Protocol,Python
Platform: UNKNOWN
Classifier: Development Status :: 5 - Production/Stable
Classifier: Environment :: Other Environment
Classifier: Intended Audience :: Developers
Classifier: Intended Audience :: Education
Classifier: License :: OSI Approved :: GNU Affero General Public License v3 or later (AGPLv3+)
Classifier: Operating System :: OS Independent
Classifier: Programming Language :: Python :: 3.7
Classifier: Programming Language :: Python :: 3.8
Classifier: Topic :: Software Development :: Libraries :: Python Modules
